fastlink/__init__.py
fastlink/base/__init__.py
fastlink/base/client.py
fastlink/base/provider.py
fastlink/base/utils.py
fastlink/constants.py
fastlink/exceptions.py
fastlink/google/__init__.py
fastlink/google/provider.py
fastlink/integrations/__init__.py
fastlink/integrations/fastapi/__init__.py
fastlink/integrations/fastapi/transport.py
fastlink/jwt/__init__.py
fastlink/jwt/manager.py
fastlink/jwt/schemas.py
fastlink/py.typed
fastlink/schemas.py
fastlink/telegram/__init__.py
fastlink/telegram/provider.py
fastlink/telegram/schemas.py
fastlink/telegram/utils.py
fastlink/yandex/__init__.py
fastlink/yandex/provider.py
fastlink-0.1.6.dist-info/LICENSE
fastlink-0.1.6.dist-info/METADATA
fastlink-0.1.6.dist-info/WHEEL
fastlink-0.1.6.dist-info/RECORD
