Metadata-Version: 2.3
Name: fastlink
Version: 0.1.6
Summary: FastLink OAuth 2.0 client for various platforms, asynchronous, easy-to-use, extensible
License: MIT
Author: everysoftware
Author-email: pravitel2015ify@gmail.com
Requires-Python: >=3.12,<4.0
Classifier: Development Status :: 4 - Beta
Classifier: Environment :: Web Environment
Classifier: Framework :: AsyncIO
Classifier: Framework :: FastAPI
Classifier: Framework :: Pydantic
Classifier: Framework :: Pydantic :: 1
Classifier: Intended Audience :: Developers
Classifier: Intended Audience :: Information Technology
Classifier: Intended Audience :: System Administrators
Classifier: License :: OSI Approved :: MIT License
Classifier: Operating System :: OS Independent
Classifier: Programming Language :: Python
Classifier: Programming Language :: Python :: 3
Classifier: Programming Language :: Python :: 3.12
Classifier: Programming Language :: Python :: 3.13
Classifier: Programming Language :: Python :: 3 :: Only
Classifier: Programming Language :: Python :: 3.11
Classifier: Topic :: Internet
Classifier: Topic :: Internet :: WWW/HTTP
Classifier: Topic :: Internet :: WWW/HTTP :: HTTP Servers
Classifier: Topic :: Software Development
Classifier: Topic :: Software Development :: Libraries
Classifier: Topic :: Software Development :: Libraries :: Application Frameworks
Classifier: Topic :: Software Development :: Libraries :: Python Modules
Classifier: Typing :: Typed
Requires-Dist: aiogram (>=3.20.0.post0,<4.0.0)
Requires-Dist: fastapi[standart] (>=0.115.7,<0.116.0)
Requires-Dist: httpx (>=0.28.1,<0.29.0)
Requires-Dist: pydantic (>=2.11.5,<3.0.0)
Requires-Dist: pyjwt (>=2.10.1,<3.0.0)
Project-URL: Documentation, https://github.com/everysoftware/fastlink
Project-URL: Homepage, https://github.com/everysoftware/fastlink
Project-URL: Repository, https://github.com/everysoftware/fastlink
